realtime_crypto/__init__.py
realtime_crypto/api.py
realtime_crypto/urls.py
realtime_crypto/models/__init__.py
realtime_crypto/models/coin.py
realtime_crypto/models/crypto_websocket.py
realtime_crypto/models/statistic.py
realtime_crypto/models/types.py
realtime_crypto/models/websocket_details.py
realtime_crypto-0.0.1.dist-info/LICENSE
realtime_crypto-0.0.1.dist-info/METADATA
realtime_crypto-0.0.1.dist-info/WHEEL
realtime_crypto-0.0.1.dist-info/top_level.txt
realtime_crypto-0.0.1.dist-info/RECORD
