Metadata-Version: 2.1
Name: realtime-crypto
Version: 0.0.1
Summary: A simple CoinmarketCap API for getting cryptocurrency prices and data
Home-page: https://github.com/SanderSita/realtime-crypto
Author: SanderSita
Author-email: sandersekreve@gmail.com
Project-URL: Source, https://github.com/SanderSita/realtime-crypto
Classifier: Programming Language :: Python :: 3
Classifier: License :: OSI Approved :: MIT License
Classifier: Operating System :: OS Independent
Requires-Python: >=3.6
License-File: LICENSE
Requires-Dist: httpx
Requires-Dist: websockets
